{
    "exhibit_id": "371",
    "title": "Царь Иван Васильевич Грозный",
    "artist": "Виктор Михайлович Васнецов",
    "year": "1897",
    "description": "На картине изображен царь Иван Грозный, спускающийся по лестнице в своих палатах. В правой руке он держит четки, в левой — посох. Взгляд суровый и тяжелый, фигура величественная, одета в золотистую парчовую шубу. Фон — древнерусская архитектура, за окном зимняя Москва. Холст, масло, 247 × 132 см. Хранится в Третьяковской галерее.",
    "interesting_facts": [
        "Единственный исторический портрет в творчестве Васнецова.",
        "Идея возникла в 1878 году после переезда в Москву, завершена в 1897-м на выставке передвижников.",
        "Куплена Павлом Третьяковым прямо с выставки.",
        "Красная дорожка символизирует кровавый путь властителей Руси.",
        "Нога царя вот-вот наступит на двуглавого орла — герб, символизируя перестройку государства."
    ],
    "image_path": "data/exhibits/371.jpg",
    "style": "декоративный стиль",
    "genre": "исторический портрет"
}
