{
    "exhibit_id": "caa15996-b496-4135-a2bb-b625f69aad4d",
    "title": "Слепой Орион ищет восход солнца",
    "artist": "Никола Пуссен",
    "year": "1658",
    "style": "классицизм",
    "genre": "мифологический пейзаж",
    "description": "Картина изображает слепого мифологического героя Ориона, ощупью ищущего восход солнца с помощью спутника на плечах, в величественном пейзаже с нимфами и дикими зверями.",
    "interesting_facts": [
        "Написана по заказу Мишеля Пассара, покровителя пейзажной живописи.",
        "Вдохновлена пересказами греческой мифологии сирийского писателя Лукиана II века.",
        "Хранится в Метрополитен-музее в Нью-Йорке.",
        "Считается одним из величайших пейзажей Пуссена.",
        "Размеры: 119,1 × 182,9 см, масло на холсте."
    ],
    "image_path": "data/exhibits/caa15996-b496-4135-a2bb-b625f69aad4d.jpg",
    "additional_info": {}
}
